pdfpad/__init__.py
pdfpad/__version__.py
pdfpad/entrypoint.py
pdfpad/interface.py
pdfpad-0.1.0.dist-info/LICENSE
pdfpad-0.1.0.dist-info/METADATA
pdfpad-0.1.0.dist-info/WHEEL
pdfpad-0.1.0.dist-info/entry_points.txt
pdfpad-0.1.0.dist-info/top_level.txt
pdfpad-0.1.0.dist-info/RECORD
