Metadata-Version: 2.1
Name: pdfpad
Version: 0.1.0
Home-page: https://github.com/arseniybelkov/pdfpad
License: MIT
Requires-Python: >=3.6
License-File: LICENSE
Requires-Dist: Pillow
Requires-Dist: pdf2image
Requires-Dist: tqdm
